chambercourt/__init__.py
chambercourt/__main__.py
chambercourt/chambercourt_game.py
chambercourt/event.py
chambercourt/game.py
chambercourt/langdetect.py
chambercourt/ptext.py
chambercourt/py.typed
chambercourt/warnings_util.py
chambercourt/levels/01 Plain map.tmx
chambercourt/levels/02 Another plain map.tmx
chambercourt/levels/Brick.png
chambercourt/levels/Diamond.png
chambercourt/levels/Gap.png
chambercourt/levels/Hero.png
chambercourt/levels/Tileset.tsx
chambercourt/levels/acorn-mode-1.ttf
chambercourt/levels/app-icon.png
chambercourt/levels/title.png
chambercourt/locale/el/LC_MESSAGES/chambercourt.mo
chambercourt/locale/fr/LC_MESSAGES/chambercourt.mo
chambercourt/locale/pt_BR/LC_MESSAGES/chambercourt.mo
chambercourt/locale/ro/LC_MESSAGES/chambercourt.mo
chambercourt/locale/sr/LC_MESSAGES/chambercourt.mo
chambercourt/locale/sv/LC_MESSAGES/chambercourt.mo
chambercourt/locale/uk/LC_MESSAGES/chambercourt.mo
chambercourt-0.9.26.dist-info/COPYING
chambercourt-0.9.26.dist-info/METADATA
chambercourt-0.9.26.dist-info/WHEEL
chambercourt-0.9.26.dist-info/entry_points.txt
chambercourt-0.9.26.dist-info/top_level.txt
chambercourt-0.9.26.dist-info/RECORD
