Metadata-Version: 2.2
Name: ChamberCourt
Version: 0.9.26
Summary: Simple 2D grid game framework based on PyGame
Author-email: Reuben Thomas <rrt@sc3d.org>
License: GPL v3 or later
Project-URL: Homepage, https://github.com/rrthomas/chambercourt
Classifier: Environment :: X11 Applications
Classifier: Environment :: MacOS X
Classifier: Environment :: Win32 (MS Windows)
Classifier: Topic :: Games/Entertainment
Classifier: Programming Language :: Python :: 3
Requires-Python: >=3.12
License-File: COPYING
Requires-Dist: i18nparse
Requires-Dist: platformdirs
Requires-Dist: pygame>=2.0.0
Requires-Dist: pyscroll
Requires-Dist: pytmx
